{
  "date": "2026-02-12",
  "terminal": "T1",
  "lastUpdated": "2026-02-12T23:21:38.741683",
  "hourlyData": [
    {
      "hour": "00~01",
      "hourStart": 0,
      "arrival": {
        "AB": 493,
        "C": 0,
        "D": 0,
        "EF": 0,
        "total": 493
      },
      "departure": {
        "AB": 0,
        "C": 1092,
        "D": 0,
        "EF": 0,
        "total": 1092
      }
    },
    {
      "hour": "01~02",
      "hourStart": 1,
      "arrival": {
        "AB": 1166,
        "C": 0,
        "D": 0,
        "EF": 0,
        "total": 1166
      },
      "departure": {
        "AB": 0,
        "C": 314,
        "D": 0,
        "EF": 0,
        "total": 314
      }
    },
    {
      "hour": "02~03",
      "hourStart": 2,
      "arrival": {
        "AB": 236,
        "C": 0,
        "D": 0,
        "EF": 0,
        "total": 236
      },
      "departure": {
        "AB": 0,
        "C": 51,
        "D": 0,
        "EF": 0,
        "total": 51
      }
    },
    {
      "hour": "03~04",
      "hourStart": 3,
      "arrival": {
        "AB": 0,
        "C": 0,
        "D": 0,
        "EF": 0,
        "total": 0
      },
      "departure": {
        "AB": 0,
        "C": 308,
        "D": 0,
        "EF": 0,
        "total": 308
      }
    },
    {
      "hour": "04~05",
      "hourStart": 4,
      "arrival": {
        "AB": 744,
        "C": 0,
        "D": 0,
        "EF": 0,
        "total": 744
      },
      "departure": {
        "AB": 0,
        "C": 1907,
        "D": 0,
        "EF": 0,
        "total": 1907
      }
    },
    {
      "hour": "05~06",
      "hourStart": 5,
      "arrival": {
        "AB": 1676,
        "C": 0,
        "D": 0,
        "EF": 179,
        "total": 1855
      },
      "departure": {
        "AB": 527,
        "C": 2946,
        "D": 0,
        "EF": 226,
        "total": 3699
      }
    },
    {
      "hour": "06~07",
      "hourStart": 6,
      "arrival": {
        "AB": 1401,
        "C": 918,
        "D": 914,
        "EF": 861,
        "total": 4094
      },
      "departure": {
        "AB": 1096,
        "C": 915,
        "D": 1140,
        "EF": 185,
        "total": 3336
      }
    },
    {
      "hour": "07~08",
      "hourStart": 7,
      "arrival": {
        "AB": 1081,
        "C": 178,
        "D": 177,
        "EF": 1686,
        "total": 3122
      },
      "departure": {
        "AB": 1449,
        "C": 1215,
        "D": 1299,
        "EF": 204,
        "total": 4167
      }
    },
    {
      "hour": "08~09",
      "hourStart": 8,
      "arrival": {
        "AB": 1402,
        "C": 169,
        "D": 169,
        "EF": 529,
        "total": 2269
      },
      "departure": {
        "AB": 1933,
        "C": 1655,
        "D": 1697,
        "EF": 288,
        "total": 5573
      }
    },
    {
      "hour": "09~10",
      "hourStart": 9,
      "arrival": {
        "AB": 1139,
        "C": 84,
        "D": 83,
        "EF": 645,
        "total": 1951
      },
      "departure": {
        "AB": 1756,
        "C": 1577,
        "D": 1673,
        "EF": 279,
        "total": 5285
      }
    },
    {
      "hour": "10~11",
      "hourStart": 10,
      "arrival": {
        "AB": 196,
        "C": 580,
        "D": 583,
        "EF": 579,
        "total": 1938
      },
      "departure": {
        "AB": 1450,
        "C": 1454,
        "D": 1565,
        "EF": 250,
        "total": 4719
      }
    },
    {
      "hour": "11~12",
      "hourStart": 11,
      "arrival": {
        "AB": 717,
        "C": 556,
        "D": 561,
        "EF": 1623,
        "total": 3457
      },
      "departure": {
        "AB": 1143,
        "C": 1341,
        "D": 1506,
        "EF": 232,
        "total": 4222
      }
    },
    {
      "hour": "12~13",
      "hourStart": 12,
      "arrival": {
        "AB": 808,
        "C": 803,
        "D": 513,
        "EF": 1322,
        "total": 3446
      },
      "departure": {
        "AB": 1012,
        "C": 1177,
        "D": 1285,
        "EF": 180,
        "total": 3654
      }
    },
    {
      "hour": "13~14",
      "hourStart": 13,
      "arrival": {
        "AB": 1032,
        "C": 577,
        "D": 301,
        "EF": 1133,
        "total": 3043
      },
      "departure": {
        "AB": 885,
        "C": 1013,
        "D": 1168,
        "EF": 167,
        "total": 3233
      }
    },
    {
      "hour": "14~15",
      "hourStart": 14,
      "arrival": {
        "AB": 1415,
        "C": 242,
        "D": 242,
        "EF": 1504,
        "total": 3403
      },
      "departure": {
        "AB": 913,
        "C": 923,
        "D": 1015,
        "EF": 134,
        "total": 2985
      }
    },
    {
      "hour": "15~16",
      "hourStart": 15,
      "arrival": {
        "AB": 1645,
        "C": 512,
        "D": 511,
        "EF": 871,
        "total": 3539
      },
      "departure": {
        "AB": 1098,
        "C": 880,
        "D": 894,
        "EF": 144,
        "total": 3016
      }
    },
    {
      "hour": "16~17",
      "hourStart": 16,
      "arrival": {
        "AB": 1067,
        "C": 306,
        "D": 305,
        "EF": 830,
        "total": 2508
      },
      "departure": {
        "AB": 1217,
        "C": 857,
        "D": 852,
        "EF": 125,
        "total": 3051
      }
    },
    {
      "hour": "17~18",
      "hourStart": 17,
      "arrival": {
        "AB": 937,
        "C": 232,
        "D": 336,
        "EF": 1579,
        "total": 3084
      },
      "departure": {
        "AB": 1176,
        "C": 870,
        "D": 939,
        "EF": 106,
        "total": 3091
      }
    },
    {
      "hour": "18~19",
      "hourStart": 18,
      "arrival": {
        "AB": 1758,
        "C": 91,
        "D": 91,
        "EF": 785,
        "total": 2725
      },
      "departure": {
        "AB": 1210,
        "C": 1023,
        "D": 987,
        "EF": 143,
        "total": 3363
      }
    },
    {
      "hour": "19~20",
      "hourStart": 19,
      "arrival": {
        "AB": 2173,
        "C": 269,
        "D": 271,
        "EF": 1537,
        "total": 4250
      },
      "departure": {
        "AB": 949,
        "C": 969,
        "D": 1007,
        "EF": 190,
        "total": 3115
      }
    },
    {
      "hour": "20~21",
      "hourStart": 20,
      "arrival": {
        "AB": 1065,
        "C": 724,
        "D": 723,
        "EF": 494,
        "total": 3006
      },
      "departure": {
        "AB": 0,
        "C": 2015,
        "D": 0,
        "EF": 140,
        "total": 2155
      }
    },
    {
      "hour": "21~22",
      "hourStart": 21,
      "arrival": {
        "AB": 1721,
        "C": 387,
        "D": 386,
        "EF": 1393,
        "total": 3887
      },
      "departure": {
        "AB": 0,
        "C": 1385,
        "D": 0,
        "EF": 94,
        "total": 1479
      }
    },
    {
      "hour": "22~23",
      "hourStart": 22,
      "arrival": {
        "AB": 2458,
        "C": 0,
        "D": 0,
        "EF": 780,
        "total": 3238
      },
      "departure": {
        "AB": 0,
        "C": 1069,
        "D": 0,
        "EF": 0,
        "total": 1069
      }
    },
    {
      "hour": "23~00",
      "hourStart": 23,
      "arrival": {
        "AB": 761,
        "C": 0,
        "D": 0,
        "EF": 0,
        "total": 761
      },
      "departure": {
        "AB": 0,
        "C": 550,
        "D": 0,
        "EF": 0,
        "total": 550
      }
    }
  ]
}