{
  "date": "2026-03-04",
  "terminal": "T1",
  "lastUpdated": "2026-03-04T14:41:29.981606",
  "hourlyData": [
    {
      "hour": "00~01",
      "hourStart": 0,
      "arrival": {
        "AB": 333,
        "C": 0,
        "D": 0,
        "EF": 0,
        "total": 333
      },
      "departure": {
        "AB": 0,
        "C": 479,
        "D": 0,
        "EF": 0,
        "total": 479
      }
    },
    {
      "hour": "01~02",
      "hourStart": 1,
      "arrival": {
        "AB": 424,
        "C": 0,
        "D": 0,
        "EF": 0,
        "total": 424
      },
      "departure": {
        "AB": 0,
        "C": 154,
        "D": 0,
        "EF": 0,
        "total": 154
      }
    },
    {
      "hour": "02~03",
      "hourStart": 2,
      "arrival": {
        "AB": 162,
        "C": 0,
        "D": 0,
        "EF": 0,
        "total": 162
      },
      "departure": {
        "AB": 0,
        "C": 46,
        "D": 0,
        "EF": 0,
        "total": 46
      }
    },
    {
      "hour": "03~04",
      "hourStart": 3,
      "arrival": {
        "AB": 0,
        "C": 0,
        "D": 0,
        "EF": 0,
        "total": 0
      },
      "departure": {
        "AB": 0,
        "C": 184,
        "D": 0,
        "EF": 0,
        "total": 184
      }
    },
    {
      "hour": "04~05",
      "hourStart": 4,
      "arrival": {
        "AB": 537,
        "C": 0,
        "D": 0,
        "EF": 0,
        "total": 537
      },
      "departure": {
        "AB": 0,
        "C": 983,
        "D": 0,
        "EF": 0,
        "total": 983
      }
    },
    {
      "hour": "05~06",
      "hourStart": 5,
      "arrival": {
        "AB": 1570,
        "C": 0,
        "D": 0,
        "EF": 0,
        "total": 1570
      },
      "departure": {
        "AB": 0,
        "C": 2330,
        "D": 0,
        "EF": 113,
        "total": 2443
      }
    },
    {
      "hour": "06~07",
      "hourStart": 6,
      "arrival": {
        "AB": 1982,
        "C": 691,
        "D": 1575,
        "EF": 0,
        "total": 4248
      },
      "departure": {
        "AB": 878,
        "C": 1152,
        "D": 438,
        "EF": 123,
        "total": 2591
      }
    },
    {
      "hour": "07~08",
      "hourStart": 7,
      "arrival": {
        "AB": 988,
        "C": 187,
        "D": 175,
        "EF": 1285,
        "total": 2635
      },
      "departure": {
        "AB": 1189,
        "C": 931,
        "D": 998,
        "EF": 129,
        "total": 3247
      }
    },
    {
      "hour": "08~09",
      "hourStart": 8,
      "arrival": {
        "AB": 1174,
        "C": 69,
        "D": 69,
        "EF": 582,
        "total": 1894
      },
      "departure": {
        "AB": 1385,
        "C": 1168,
        "D": 1230,
        "EF": 165,
        "total": 3948
      }
    },
    {
      "hour": "09~10",
      "hourStart": 9,
      "arrival": {
        "AB": 710,
        "C": 78,
        "D": 78,
        "EF": 734,
        "total": 1600
      },
      "departure": {
        "AB": 1124,
        "C": 1056,
        "D": 1176,
        "EF": 131,
        "total": 3487
      }
    },
    {
      "hour": "10~11",
      "hourStart": 10,
      "arrival": {
        "AB": 86,
        "C": 446,
        "D": 446,
        "EF": 564,
        "total": 1542
      },
      "departure": {
        "AB": 954,
        "C": 1016,
        "D": 1190,
        "EF": 171,
        "total": 3331
      }
    },
    {
      "hour": "11~12",
      "hourStart": 11,
      "arrival": {
        "AB": 914,
        "C": 852,
        "D": 636,
        "EF": 1507,
        "total": 3909
      },
      "departure": {
        "AB": 758,
        "C": 970,
        "D": 1165,
        "EF": 171,
        "total": 3064
      }
    },
    {
      "hour": "12~13",
      "hourStart": 12,
      "arrival": {
        "AB": 801,
        "C": 852,
        "D": 559,
        "EF": 1070,
        "total": 3282
      },
      "departure": {
        "AB": 753,
        "C": 839,
        "D": 1020,
        "EF": 140,
        "total": 2752
      }
    },
    {
      "hour": "13~14",
      "hourStart": 13,
      "arrival": {
        "AB": 865,
        "C": 624,
        "D": 314,
        "EF": 1751,
        "total": 3554
      },
      "departure": {
        "AB": 688,
        "C": 734,
        "D": 857,
        "EF": 103,
        "total": 2382
      }
    },
    {
      "hour": "14~15",
      "hourStart": 14,
      "arrival": {
        "AB": 1276,
        "C": 298,
        "D": 297,
        "EF": 1198,
        "total": 3069
      },
      "departure": {
        "AB": 568,
        "C": 671,
        "D": 757,
        "EF": 81,
        "total": 2077
      }
    },
    {
      "hour": "15~16",
      "hourStart": 15,
      "arrival": {
        "AB": 1777,
        "C": 544,
        "D": 543,
        "EF": 801,
        "total": 3665
      },
      "departure": {
        "AB": 628,
        "C": 608,
        "D": 648,
        "EF": 78,
        "total": 1962
      }
    },
    {
      "hour": "16~17",
      "hourStart": 16,
      "arrival": {
        "AB": 776,
        "C": 426,
        "D": 425,
        "EF": 773,
        "total": 2400
      },
      "departure": {
        "AB": 706,
        "C": 555,
        "D": 605,
        "EF": 79,
        "total": 1945
      }
    },
    {
      "hour": "17~18",
      "hourStart": 17,
      "arrival": {
        "AB": 723,
        "C": 327,
        "D": 460,
        "EF": 970,
        "total": 2480
      },
      "departure": {
        "AB": 687,
        "C": 486,
        "D": 530,
        "EF": 61,
        "total": 1764
      }
    },
    {
      "hour": "18~19",
      "hourStart": 18,
      "arrival": {
        "AB": 1641,
        "C": 64,
        "D": 63,
        "EF": 970,
        "total": 2738
      },
      "departure": {
        "AB": 599,
        "C": 536,
        "D": 533,
        "EF": 54,
        "total": 1722
      }
    },
    {
      "hour": "19~20",
      "hourStart": 19,
      "arrival": {
        "AB": 1623,
        "C": 123,
        "D": 126,
        "EF": 1196,
        "total": 3068
      },
      "departure": {
        "AB": 510,
        "C": 522,
        "D": 574,
        "EF": 93,
        "total": 1699
      }
    },
    {
      "hour": "20~21",
      "hourStart": 20,
      "arrival": {
        "AB": 638,
        "C": 664,
        "D": 356,
        "EF": 550,
        "total": 2208
      },
      "departure": {
        "AB": 0,
        "C": 1214,
        "D": 0,
        "EF": 79,
        "total": 1293
      }
    },
    {
      "hour": "21~22",
      "hourStart": 21,
      "arrival": {
        "AB": 1001,
        "C": 392,
        "D": 392,
        "EF": 1071,
        "total": 2856
      },
      "departure": {
        "AB": 0,
        "C": 682,
        "D": 0,
        "EF": 40,
        "total": 722
      }
    },
    {
      "hour": "22~23",
      "hourStart": 22,
      "arrival": {
        "AB": 2139,
        "C": 0,
        "D": 535,
        "EF": 382,
        "total": 3056
      },
      "departure": {
        "AB": 0,
        "C": 170,
        "D": 0,
        "EF": 0,
        "total": 170
      }
    },
    {
      "hour": "23~00",
      "hourStart": 23,
      "arrival": {
        "AB": 1125,
        "C": 0,
        "D": 0,
        "EF": 0,
        "total": 1125
      },
      "departure": {
        "AB": 0,
        "C": 1,
        "D": 0,
        "EF": 0,
        "total": 1
      }
    }
  ]
}