{
  "id": "20260425163258",
  "lastUpdated": "2026-04-25T16:32:58.907948",
  "shortTerm": {
    "floor1": {
      "available": 603,
      "name": "지상 1층"
    },
    "basement1": {
      "available": 110,
      "name": "지하 1층"
    },
    "basement2": {
      "available": 779,
      "name": "지하 2층"
    }
  },
  "longTerm": {
    "east": {
      "p1": {
        "available": 721,
        "name": "장기주차장 P1"
      },
      "tower": {
        "available": 79,
        "name": "주차타워 동편"
      },
      "p3": {
        "available": 968,
        "name": "장기주차장 P3"
      }
    },
    "west": {
      "p2": {
        "available": 803,
        "name": "장기주차장 P2"
      },
      "tower": {
        "available": 73,
        "name": "주차타워 서편"
      },
      "p4": {
        "available": 1425,
        "name": "장기주차장 P4"
      }
    }
  },
  "errors": []
}