{
  "id": "20260129163411",
  "lastUpdated": "2026-01-29T16:34:11.650093",
  "shortTerm": null,
  "longTerm": {
    "east": {
      "p1": {
        "available": 404,
        "name": "장기주차장 P1"
      },
      "tower": {
        "available": 26,
        "name": "주차타워 동편"
      },
      "p3": {
        "available": 209,
        "name": "장기주차장 P3"
      }
    },
    "west": {
      "p2": {
        "available": 265,
        "name": "장기주차장 P2"
      },
      "tower": {
        "available": 47,
        "name": "주차타워 서편"
      },
      "p4": {
        "available": 652,
        "name": "장기주차장 P4"
      }
    }
  },
  "errors": [
    "Short-term: invalid literal for int() with base 10: ''"
  ]
}