{
  "id": "20260512111339",
  "lastUpdated": "2026-05-12T11:13:39.838923",
  "shortTerm": {
    "floor1": {
      "available": 572,
      "name": "지상 1층"
    },
    "basement1": {
      "available": 133,
      "name": "지하 1층"
    },
    "basement2": {
      "available": 813,
      "name": "지하 2층"
    }
  },
  "longTerm": {
    "east": {
      "p1": {
        "available": 800,
        "name": "장기주차장 P1"
      },
      "tower": {
        "available": 36,
        "name": "주차타워 동편"
      },
      "p3": {
        "available": 1325,
        "name": "장기주차장 P3"
      }
    },
    "west": {
      "p2": {
        "available": 1486,
        "name": "장기주차장 P2"
      },
      "tower": {
        "available": 54,
        "name": "주차타워 서편"
      },
      "p4": {
        "available": 1524,
        "name": "장기주차장 P4"
      }
    }
  },
  "errors": []
}