{
  "id": "20260301161833",
  "lastUpdated": "2026-03-01T16:18:33.688664",
  "shortTerm": null,
  "longTerm": {
    "east": {
      "p1": {
        "available": 685,
        "name": "장기주차장 P1"
      },
      "tower": {
        "available": 92,
        "name": "주차타워 동편"
      },
      "p3": {
        "available": 143,
        "name": "장기주차장 P3"
      }
    },
    "west": {
      "p2": {
        "available": 601,
        "name": "장기주차장 P2"
      },
      "tower": {
        "available": 105,
        "name": "주차타워 서편"
      },
      "p4": {
        "available": 266,
        "name": "장기주차장 P4"
      }
    }
  },
  "errors": [
    "Short-term: invalid literal for int() with base 10: ''"
  ]
}