{
  "id": "20260207182409",
  "lastUpdated": "2026-02-07T18:24:09.590607",
  "shortTerm": null,
  "longTerm": {
    "east": {
      "p1": {
        "available": 442,
        "name": "장기주차장 P1"
      },
      "tower": {
        "available": 27,
        "name": "주차타워 동편"
      },
      "p3": {
        "available": 109,
        "name": "장기주차장 P3"
      }
    },
    "west": {
      "p2": {
        "available": 367,
        "name": "장기주차장 P2"
      },
      "tower": {
        "available": 36,
        "name": "주차타워 서편"
      },
      "p4": {
        "available": 82,
        "name": "장기주차장 P4"
      }
    }
  },
  "errors": [
    "Short-term: invalid literal for int() with base 10: ''"
  ]
}